alogos/__init__.py
alogos/exceptions.py
alogos/warnings.py
alogos/_grammar/__init__.py
alogos/_grammar/data_structures.py
alogos/_grammar/generation/__init__.py
alogos/_grammar/generation/language.py
alogos/_grammar/normalization/__init__.py
alogos/_grammar/normalization/_shared.py
alogos/_grammar/normalization/binary_choice.py
alogos/_grammar/normalization/chomsky.py
alogos/_grammar/normalization/greibach.py
alogos/_grammar/parsing/__init__.py
alogos/_grammar/parsing/io_with_regex.py
alogos/_grammar/parsing/parsing_with_lark.py
alogos/_grammar/visualization/__init__.py
alogos/_grammar/visualization/grammar_with_railroad.py
alogos/_grammar/visualization/tree_with_graphviz.py
alogos/_optimization/__init__.py
alogos/_optimization/ea/__init__.py
alogos/_optimization/ea/algorithm.py
alogos/_optimization/ea/database.py
alogos/_optimization/ea/parameters.py
alogos/_optimization/ea/plots.py
alogos/_optimization/ea/reporting.py
alogos/_optimization/ea/state.py
alogos/_optimization/ea/operators/__init__.py
alogos/_optimization/ea/operators/generation_model.py
alogos/_optimization/ea/operators/selection.py
alogos/_optimization/shared/__init__.py
alogos/_optimization/shared/evaluation.py
alogos/_utilities/__init__.py
alogos/_utilities/argument_processing.py
alogos/_utilities/database_management.py
alogos/_utilities/operating_system.py
alogos/_utilities/parametrization.py
alogos/_utilities/times.py
alogos/systems/__init__.py
alogos/systems/_shared/__init__.py
alogos/systems/_shared/_cached_calculations.py
alogos/systems/_shared/crossover.py
alogos/systems/_shared/init_individual.py
alogos/systems/_shared/init_population.py
alogos/systems/_shared/init_tree.py
alogos/systems/_shared/mapping.py
alogos/systems/_shared/mutation.py
alogos/systems/_shared/neighborhood.py
alogos/systems/_shared/representation.py
alogos/systems/cfggp/__init__.py
alogos/systems/cfggp/_parameters.py
alogos/systems/cfggp/crossover.py
alogos/systems/cfggp/init_individual.py
alogos-0.2.1.dist-info/LICENSE
alogos-0.2.1.dist-info/METADATA
alogos-0.2.1.dist-info/NOTICE
alogos-0.2.1.dist-info/WHEEL
alogos-0.2.1.dist-info/top_level.txt
alogos-0.2.1.dist-info/RECORD
