Metadata-Version: 2.1
Name: alogos
Version: 0.2.1
Summary: Grammar-guided genetic programming (G3P): Search for optimal strings in any context-free language.
Home-page: https://github.com/robert-haas/alogos
Author: Robert Haas
Author-email: robert.haas@protonmail.com
License: Apache License, Version 2.0
Classifier: Development Status :: 4 - Beta
Classifier: Intended Audience :: Developers
Classifier: Intended Audience :: Education
Classifier: Intended Audience :: Science/Research
Classifier: License :: OSI Approved :: Apache Software License
Classifier: Natural Language :: English
Classifier: Operating System :: OS Independent
Classifier: Programming Language :: Python :: 3
Classifier: Topic :: Scientific/Engineering
Classifier: Topic :: Scientific/Engineering :: Electronic Design Automation (EDA)
Classifier: Topic :: Software Development
Classifier: Topic :: Software Development :: Code Generators
Classifier: Topic :: Text Processing
Classifier: Topic :: Text Processing :: Linguistic
Requires-Python: >=3.6
License-File: LICENSE
License-File: NOTICE
Requires-Dist: ordered-set >=3.0
Requires-Dist: lark-parser <1,>=0.6.5
Requires-Dist: railroad-diagrams <3,>=1
Requires-Dist: pylru <2,>=1.1
Requires-Dist: gravis <1,>=0.1
Requires-Dist: bitarray <3,>2
